pab/__init__.py
pab/accounts.py
pab/alert.py
pab/blockchain.py
pab/cli.py
pab/config.py
pab/contract.py
pab/core.py
pab/init.py
pab/strategy.py
pab/task.py
pab/transaction.py
pab/utils.py
pab/resources/config.schema.json
PyAutoBlockchain-0.5.dist-info/LICENSE
PyAutoBlockchain-0.5.dist-info/METADATA
PyAutoBlockchain-0.5.dist-info/WHEEL
PyAutoBlockchain-0.5.dist-info/entry_points.txt
PyAutoBlockchain-0.5.dist-info/top_level.txt
PyAutoBlockchain-0.5.dist-info/RECORD
