Metadata-Version: 2.1
Name: PyAutoBlockchain
Version: 0.5
Summary: PAB is a framework that helps with development and automation of periodic tasks on blockchains.
Home-page: https://github.com/manuelpepe/PyAutoBlockchain
Author: Manuel Pepe
Author-email: manuelpepe-dev@outlook.com.ar
License: UNKNOWN
Platform: UNKNOWN
License-File: LICENSE
Requires-Dist: web3
Requires-Dist: hexbytes
Requires-Dist: python-dotenv
Provides-Extra: ui
Requires-Dist: pabui ; extra == 'ui'
